sbxreader/__init__.py
sbxreader/reader.py
sbxreader/reg.py
sbxreader/viewer.py
sbxreader-0.2.3.dist-info/licenses/LICENSE
sbxreader-0.2.3.dist-info/METADATA
sbxreader-0.2.3.dist-info/WHEEL
sbxreader-0.2.3.dist-info/entry_points.txt
sbxreader-0.2.3.dist-info/top_level.txt
sbxreader-0.2.3.dist-info/RECORD
