Metadata-Version: 2.4
Name: sbxreader
Version: 0.2.3
Summary: Python module to read Neurolabware Scanbox files.
Home-page: https://github.com/jcouto/sbxreader
Author: Joao Couto
Author-email: jpcouto@gmail.com
License: GPL
License-File: LICENSE
Requires-Dist: scipy
Dynamic: author
Dynamic: author-email
Dynamic: description
Dynamic: description-content-type
Dynamic: home-page
Dynamic: license
Dynamic: license-file
Dynamic: requires-dist
Dynamic: summary
